shamir.py
shamir-17.12.0.dist-info/DESCRIPTION.rst
shamir-17.12.0.dist-info/METADATA
shamir-17.12.0.dist-info/RECORD
shamir-17.12.0.dist-info/WHEEL
shamir-17.12.0.dist-info/metadata.json
shamir-17.12.0.dist-info/top_level.txt
