Metadata-Version: 2.0
Name: shamir
Version: 17.12.0
Summary: UNKNOWN
Home-page: https://github.com/kurtbrose/shamir
Author: Kurt Rose
Author-email: kurt@kurtrose.com
License: UNKNOWN
Platform: UNKNOWN
